event_transforms_pandas/__init__.py
event_transforms_pandas/coalesce.py
event_transforms_pandas-0.0.1.dist-info/LICENCE
event_transforms_pandas-0.0.1.dist-info/METADATA
event_transforms_pandas-0.0.1.dist-info/WHEEL
event_transforms_pandas-0.0.1.dist-info/top_level.txt
event_transforms_pandas-0.0.1.dist-info/RECORD
